{"product_name":"QVHelper","build_number":"33","build_type":"build_adhoc","version":"3.0.0","time":"2021-04-16_15_49","download_path":"http://10.0.32.65:8888/QVHelper/QVHelper_3.0.0_build_adhoc_33_2021-04-16_15_49.ipa","jenkins_path":"http://10.0.32.65:8080/job/iOS%20AutoBuild%20QVHelper/33/","changelog":"* [SandsLee] fix: 自归因测试模式\\n* [SandsLee] fix: 清空剪切板\\n* [SandsLee] fix: 清空剪切板\\n* [SandsLee] feat: 归因3.0版本测试专用\\n* [SandsLee] feat: 归因3.0版本测试专用\\n* [SandsLee] feat: 归因3.0版本测试专用\\n* [SandsLee] feat: 归因3.0版本测试专用\\n* [SandsLee] fix: 自动获取公网IP\\n* [SandsLee] fix: 调整归因测试链接生成规则，如果idfa取不到则不拼接到链接中\\n* [SandsLee] feat: 新增快手归因测试"}