{"product_name":"QVHelper","build_number":"51","build_type":"build_adhoc","version":"3.0.0","time":"2021-07-16_10_53","download_path":"http://10.0.32.32:8888/QVHelper/QVHelper_3.0.0_build_adhoc_51_2021-07-16_10_53.ipa","jenkins_path":"http://10.0.32.129:8080/job/iOS%20AutoBuild%20QVHelper/51/","changelog":"* [SandsLee] fix: 新增自定义隔离环境，支持隔离App的自定义域名\\n* [SandsLee] fix: 更新小影scheme\\n* [SandsLee] fix: 自归因测试模式\\n* [SandsLee] fix: 清空剪切板\\n* [SandsLee] fix: 清空剪切板\\n* [SandsLee] feat: 归因3.0版本测试专用\\n* [SandsLee] feat: 归因3.0版本测试专用\\n* [SandsLee] feat: 归因3.0版本测试专用\\n* [SandsLee] feat: 归因3.0版本测试专用\\n* [SandsLee] fix: 自动获取公网IP"}