{"product_name":"MemeZoo","build_number":"59","build_type":"build_adhoc","version":"0.1.0","branch":"origin/editor_dev","time":"2024-05-27_19_47","download_path":"http://10.0.32.62:8888/MemeZoo/0.1.0_build_adhoc_59_2024-05-27_19_47.ipa","jenkins_path":"http://10.0.32.129:8080/job/iOS%20AutoBuild%20MemeZoo/59/","changelog":"[yarong] fix: 文字枚举调整\\n[yarong] fix: 安卓兼容问题\\n[yarong] fix: 逻辑调整；图层复杂卡顿问题\\n[sheepzhangzhang] feat: 解决拖拽黑色阴影\\n[sheepzhangzhang] feat: 重置加载更多状态\\n[yarong] fix: UI调整\\n[sheepzhangzhang] feat: 加载数据优化\\n[yarong] fix: 导出橡皮擦展示问题\\n[yarong] fix: 逻辑调优\\n[sheepzhangzhang] feat: 优化数据加载"}