{"product_name":"VivaVideo","build_number":"643","build_type":"build_adhoc","version":"8.7.0","time":"2021-01-22_22_20","download_path":"http://10.0.32.129:8888/VivaVideo/8.7.0_build_adhoc_643_2021-01-22_22_20.ipa","jenkins_path":"http://10.0.32.129:8080/job/iOS%20AutoBuild%VivaVideo/643/","changelog":"* [XXY] chore: 更新podfile\\n* [XXY] chore: 更新podlock\\n* [yarong] feat: 避风港需求\\n* [yarong] feat: 分享 跟 评分 走config\\n* [XXY] chore: 更新podfile\\n* [XXY] feat: version 8.7.0 appkey 200273\\n* [XXY] chore: 更新podfile\\n* [XXY] feat: 新增XYVivaRouteModuleService\\n* [XXY] chore: XYVivaEditor先指向分支\\n* [tezhou] fix：podLock"}