{"product_name":"VivaVideo","build_number":"1303","build_type":"build_adhoc","version":"8.11.5","time":"2021-09-06_19_27","download_path":"http://10.0.32.32:8888/VivaVideo/8.11.5_build_adhoc_1303_2021-09-06_19_27.ipa","jenkins_path":"http://10.0.32.129:8080/job/iOS%20AutoBuild%VivaVideo/1303/","changelog":"* [zhaoyunyi] fix: Podfile Updated\\n* [徐新元] fix: engine_ios_sdk_delivery_#27486_20210903_patch_jenkins\\n* [徐新元] fix: 修复进入模版页的时候，模版曝光事件ContentPage_Template_Show没有上报的问题\\n* [yite] fix：更新podfile\\n* [zhaoyunyi] fix: strings updated\\n* [yarong] fix: 更新podfile & podlock\\n* [yarong] fix: 更新podfile & podlock\\n* [yite] fix：增加广告监测字段false\\n* [yarong] fix: 更新podfile podlock\\n* [yarong] fix: 更新podfile 和 podlock"}