{"product_name":"VivaVideo","build_number":"4612","build_type":"build_adhoc","version":"9.22.0","time":"2024-11-05_12_46","branch":"origin/9.22.0","download_path":"http://10.0.32.62:8888/VivaVideo/9.22.0_build_adhoc_4612_2024-11-05_12_46.ipa","jenkins_path":"http://10.0.32.129:8080/job/iOS%20AutoBuild%20VivaVideo/4612/","changelog":"引擎包:#define GLOABLE_SVN_MASTER_VERSION 8.17.22\\n [Sands] feat: loco 字符串更新\\n [Sands] fix: podfile 修复Xcode 16 FMDB引用及Framework的BitCode剥离\\n [yueshan] feat:podfile更新\\n [yueshan] feat:podfile更新\\n [yueshan] feat: podfile更新\\n [yueshan] feat:podfile更新\\n [yueshan] feat：podfile更新\\n [yueshan] feat: podfile更改\\n [Sands] feat: podfile 更新\\n [Sands] feat: loco 字符串更新"}