{"product_name":"VivaVideo","build_number":"864","build_type":"build_adhoc","version":"8.8.7","time":"2021-04-21_16_58","download_path":"http://10.0.32.129:8888/VivaVideo/8.8.7_build_adhoc_864_2021-04-21_16_58.ipa","jenkins_path":"http://10.0.32.129:8080/job/iOS%20AutoBuild%VivaVideo/864/","changelog":"* [yite] fix：更新podfile\\n* [徐新元] feat: 积分墙归因上报（加密idfa参数）\\n* [徐新元] feat: version 8.8.7 appkey 200283\\n* [yite] fix：adcore版本\\n* [yarong] fix: podfile更新\\n* [yite] fix：adcore版本\\n* [yite] fix：广告版本号\\n* [徐新元] feat: 不同意隐私政策的情况下，不自动上传日志文件，且不上传idfa等敏感数据\\n* [yarong] feat: podfile 更新\\n* [yite] fix：更新podfile"}