{"product_name":"VivaVideo","build_number":"380","build_type":"build_adhoc","version":"8.4.8","time":"2020-09-25_19_39","download_path":"http://10.0.32.129:8888/VivaVideo/8.4.8_build_adhoc_380_2020-09-25_19_39.ipa","jenkins_path":"http://10.0.32.129:8080/job/iOS%20AutoBuild%VivaVideo/380/","changelog":"* [Frenzy] 【update】24112_202009231701_jenkins.zip\\n* [Frenzy] 【update】  - ApplinsSDK (4.4.1)   - XYVivaInitialize (8.4.8-1): 问题duid重新设备注册\\n* [徐新元] feat: 更新字符串\\n* [tezhou] 归因组件更新\\n* [徐新元] chore: 更新podlock\\n* [tezhou] 去除无用Pod\\n* [徐新元] chore: 更新podlock\\n* [Darren] update string\\n* [徐新元] feat: 国内隐私条款相关逻辑修改\\n* [徐新元] feat: 添加国内隐私条款预置简单版html页面"}