{"product_name":"VivaVideo","build_number":"5502","build_type":"build_adhoc","version":"9.29.0","time":"2025-07-10_17_29","branch":"origin/9.29.0","download_path":"http://10.0.32.125:8888/VivaVideo/9.29.0_build_adhoc_5502_2025-07-10_17_29.ipa","jenkins_path":"http://10.0.32.129:8080/job/iOS%20AutoBuild%20VivaVideo/5502/","changelog":"引擎包:#define GLOABLE_SVN_MASTER_VERSION 8.22.10\\n [FengmingXiao] fix:修改埋点字段\\n [bolun.chen] feat:创作者信息\\n [yueshan] feat：埋点配置\\n [yueshan] feat: 增加埋点参数\\n [FengmingXiao] feat:更新Podfile\\n [FengmingXiao] fix:修复编辑菜单栏问题\\n [yueshan] feat：更新版本号 & appKey\\n [yueshan] feat:podfile更新 & 数据库升级\\n [FengmingXiao] feat:修改Podfile.lock\\n [FengmingXiao] feat:更新Podfile.lock"}