{"product_name":"AITemplate","build_number":"132","build_type":"build_adhoc","version":"1.0.4","branch":"origin/release/1.0.4","time":"2025-02-10_17_50","download_path":"http://10.0.32.62:8888/AITemplate/1.0.4_build_adhoc_132_2025-02-10_17_50.ipa","jenkins_path":"http://10.0.32.129:8080/job/iOS%20AutoBuild%20AITemplate/132/","changelog":"[qufanrong] add upload tip type\\n[qufanrong] domain整理\\n[qufanrong] 1.0.4需求开发\\n[qufanrong] 1.0.4\\n[qufanrong] change podfile\\n[qufanrong] 1.0.3\\n[qufanrong] remove handyJSON\\n[qufanrong] idfa info message\\n[chaojie.zheng] feat(scope): 埋点debug\\n[qufanrong] change podfile"}