{"product_name":"VMix","build_number":"218","build_type":"build_adhoc","version":"1.1.6","time":"2021-07-05_14_56","branch":"dev_1.1.6","download_path":"http://10.0.32.129:8888/VMix/VMix_1.1.6_dev_1.1.6_build_adhoc_218_2021-07-05_14_56.ipa","jenkins_path":"http://10.0.32.129:8080/job/iOS%20AutoBuild%VMix/218/","changelog":"* [fmxfmx] feat: 1. 修改默认域名配置\\n* [Richard] fix #OVI-342 预览进度条粗细不一制\\n* [Richard] fix #OVI-345 修复转场替换成功标题没刷新\\n* [Richard] fix #OVI-343 无片段时不显示预览\\n* [Richard] Appkey: 20000500  Version: 1.1.6\\n* [Richard] fix #OVI-347 字体封面异常\\n* [yvan] fix： 1.正在预览问题修复\\n* [yvan] fix: 1.修改转场出现重播按钮的逻辑\\n* [Richard] fix #OVI-340 贴纸列表封面被被裁切\\n* [fmxfmx] fix: 1. 修改线上音频播放器seek问题"}