{"product_name":"VMix","build_number":"37","build_type":"build_adhoc","version":"","time":"2021-03-26_13_56","branch":"dev_1.0","download_path":"http://10.0.32.129:8888/VMix/VMix__dev_1.0_build_adhoc_37_2021-03-26_13_56.ipa","jenkins_path":"http://10.0.32.129:8080/job/iOS%20AutoBuild%VMix/37/","changelog":"* [ioscommon] fix: update development team\\n* [robbin] feat(在线素材): 更大的选中外边框\\n* [robbin] feat(在线素材): 显示作者而不是album\\n* [Richard] fix: 修复预裁剪操作后播放器被移除\\n* [Richard] fix: 修复草稿进入画中画缩略图消失\\n* [Sunshine] feat: 添加导出失败ui 及 fix 预览取消问题\\n* [yvan] fix: 1.修复字幕行间距重载显示问题\\n* [yvan] feat：弹窗UI搭建\\n* [fmxfmx] fix(引擎功能)： 1. 修改编译问题\\n* [fmxfmx] fix(引擎功能): 1. 修改片段变速后移动时长设置问题 2. 修改undo，redo后引擎黑帧无效问题"}