{"product_name":"Rythmix","build_number":"2","build_type":"build_adhoc","version":"1.0.0","branch":"origin/dev","time":"2024-10-25_11_33","download_path":"http://10.0.32.62:8888/Rythmix/1.0.0_build_adhoc_2_2024-10-25_11_33.ipa","jenkins_path":"http://10.0.32.129:8080/job/iOS%20AutoBuild%20Rythmix/2/","changelog":"[yarong] feat: 部分字符串替换\\n[yarong] feat: 字符串添加\\n[yarong] feat: 封面调整\\n[sheepzhangzhang] feat: 跑马灯效果\\n[yarong] feat: 保存歌曲\\n[sheepzhangzhang] feat: 句尾...展示\\n[sheepzhangzhang] feat: 可选类型\\n[sheepzhangzhang] feat: 编辑弹框\\n[sheepzhangzhang] feat: 完善更改歌曲名、封面图交互细节\\n[yarong] feat: 数据填充"}