{"product_name":"Rythmix","build_number":"18","build_type":"build_adhoc","version":"1.0.0","branch":"origin/dev","time":"2024-10-30_11_53","download_path":"http://10.0.32.62:8888/Rythmix/1.0.0_build_adhoc_18_2024-10-30_11_53.ipa","jenkins_path":"http://10.0.32.129:8080/job/iOS%20AutoBuild%20Rythmix/18/","changelog":"[yarong] fix: 首次非会员弹订阅\\n[yarong] fix: icon 替换；ts添加过期日期；履约调用一次\\n[sheepzhangzhang] feat: 隐藏滚动条\\n[yarong] fix: restore 后履约上报多次问题\\n[sheepzhangzhang] feat: 刷新通知，键盘收起\\n[yarong] fix: 自动播放状态\\n[yarong] fix:  播放栏状态记录；任务集/作品集请求提前；播放状态更新\\n[yarong] fix: 唱针状态；slider滑动不阻碍播放\\n[yarong] fix: 歌词模式强toast提示\\n[yarong] fix: 过滤空格"}