{"product_name":"EngineApp","build_number":"440","build_type":"build_adhoc","version":"1.0","time":"2023-04-06_20_41","download_path":"http://10.0.32.62:8888/EngineApp/1.0_build_adhoc_440_2023-04-06_20_41.ipa","jenkins_path":"http://10.0.32.129:8080/job/iOS%20AutoBuild%EngineApp/440/","changelog":"* [Sunhine] feat: fix bug\\n* [Sunhine] feat: 优化\\n* [Sunhine] feat: toast\\n* [Sunhine] feat: toast\\n* [Sunhine] feat: xiu fu\\n* [Sunhine] feat：fix bug\\n* [Sunhine] fix: bug\\n* [Sunhine] feat: fix bug\\n* [Sunhine] feat: 代码整理 修复切换问题\\n* [Sunhine] feat: 角色替换"}