{"product_name":"EngineApp","build_number":"31","build_type":"build_adhoc","version":"1.0","time":"2022-05-27_15_56","download_path":"http://10.0.32.62:8888/EngineApp/1.0_build_adhoc_31_2022-05-27_15_56.ipa","jenkins_path":"http://10.0.32.129:8080/job/iOS%20AutoBuild%EngineApp/31/","changelog":"* [Alex] fix：update podfile\\n* [Alex] fix：close bitcode\\n* [Alex] feat：update podfile\\n* [Alex] fix：add pod source\\n* [Alex] feat：auto test demo code\\n* [Sunshine] feat: 优化demo\\n* [Sunshine] feat： fix team id\\n* [Sunshine] feat：team 切换\\n* [Sunshine] feat：boundID fix\\n* [Sunshine] feat: boundid 更改"}