{"product_name":"EngineApp","build_number":"119","build_type":"build_adhoc","version":"1.0","time":"2022-08-19_20_34","download_path":"http://10.0.32.62:8888/EngineApp/1.0_build_adhoc_119_2022-08-19_20_34.ipa","jenkins_path":"http://10.0.32.129:8080/job/iOS%20AutoBuild%EngineApp/119/","changelog":"* [Alex] fix：upload pic error\\n* [Sunhine] feat: josn\\n* [Sunhine] feat: fix\\n* [Sunhine] feat: fix bug\\n* [Sunhine] feat: ui\\n* [Alex] fix：demo upload error\\n* [Sunhine] feat：demo fix\\n* [Alex] fix：合成失败error信息更新\\n* [Alex] fix：ovc manager alloc forward\\n* [Alex] fix：podfile update"}