{"product_name":"WiseMeal","build_number":"192","build_type":"build_adhoc","version":"1.0.4","branch":"origin/1.0.2","time":"2025-04-15_16_35","download_path":"http://10.0.32.62:8888/WiseMeal/1.0.4_build_adhoc_192_2025-04-15_16_35.ipa","jenkins_path":"http://10.0.32.129:8080/job/iOS%20AutoBuild%20WiseMeal/192/","changelog":"[chaojie.zheng] feat(scope): kf-sd\\n[chaojie.zheng] feat(scope): 104 FB 升级提前发版\\n[chaojie.zheng] feat(scope): Fb 更新\\n[chaojie.zheng] feat(scope): build 5\\n[chaojie.zheng] feat(scope): build 4\\n[chaojie.zheng] feat(scope): build 3\\n[chaojie.zheng] feat(scope): 新增key 将 SKAN 回发副本发送至 AppsFlyer\\n[chaojie.zheng] feat(scope): 103\\n[chaojie.zheng] feat(scope): build 13\\n[chaojie.zheng] feat(scope): 多语言更新  build 12"}