{"product_name":"Tempo","build_number":"220","build_type":"build_adhoc","version":"3.23.0","time":"2022-01-20_14_08","download_path":"http://10.0.32.32:8888/Tempo/3.23.0_build_adhoc_220_2022-01-20_14_08.ipa","jenkins_path":"http://10.0.32.129:8080/job/iOS%20AutoBuild%Tempo/220/","changelog":"[chaojie.zheng] feat(scope):fix\\n[chaojie.zheng] feat(scope): att change\\n[liweikun] tf包\\n[liweikun] podfile修改\\n[Lihaiyang] 修改翻译文案\\n[liweikun] 多语言\\n[Lihaiyang] 修改locol脚本运行方式\\n[liweikun] 冷启动使用缓存的config自动关闭时间\\n[liweikun] podfile修改\\n[chaojie.zheng] feat(scope): 开屏ad关闭自动倒计时"}