{"product_name":"Tempo","build_number":"233","build_type":"build_adhoc","version":"3.24.1","branch":"origin/Engine_Dev","time":"2022-02-17_14_51","download_path":"http://10.0.32.62:8888/Tempo/3.24.1_build_adhoc_233_2022-02-17_14_51.ipa","jenkins_path":"http://10.0.32.129:8080/job/iOS%20AutoBuild%Tempo/233/","changelog":"[chaojie.zheng] feat(scope): 替换引擎包\\n[Peter] feat: 加入router\\n[Peter] feat: 优化脚本\\n[Peter] feat: 修复路径脚本问题\\n[Peter] 提交合并分支\\n[liweikun] 忽略podfile.path\\n[Peter] feat:vignore\\n[liweikun] 3.24.1\\n[Lihaiyang] 多语言\\n 处理\\n[chaojie.zheng] feat(scope): \\n"}