{"product_name":"Tempo","build_number":"512","build_type":"build_adhoc","version":"4.13.0","branch":"origin/4.14.0","time":"2022-08-02_14_48","download_path":"http://10.0.32.62:8888/Tempo/4.13.0_build_adhoc_512_2022-08-02_14_48.ipa","jenkins_path":"http://10.0.32.129:8080/job/iOS%20AutoBuild%Tempo/512/","changelog":"[chaojie.zheng] feat(scope): string\\n[liweikun] 新接入广告中介\\n[liweikun] 多语言\\n[chaojie.zheng] feat(scope): 4.14.0 appkey++\\n[liweikun] 引擎更新\\n[liweikun] 固定lottie版本\\n[chaojie.zheng] feat(scope): 修改分支\\n[chaojie.zheng] feat(scope): 订阅页弹出方式修改\\n[chaojie.zheng] feat(scope): 分支\\n[Peter] feat: 修改podfile"}