{"product_name":"VivaCut","build_number":"2093","build_type":"build_adhoc","version":"2.13.0","time":"2022-05-16_14_52","branch":"dev_2.13.0_feat_trim_thumbnail","download_path":"http://10.0.32.32:8888/VivaCut/VivaCut_2.13.0_dev_2.13.0_feat_trim_thumbnail_build_adhoc_2093_2022-05-16_14_52.ipa","jenkins_path":"http://10.0.32.32:8080/job/iOS%20AutoBuild%VivaCut/2093/","changelog":"[zhangqifan] feat: 更新字符串\\n[zhangqifan] fix: Podfile\\n[zhangqifan] fix: Podfile\\n[zhangqifan] feat: 更改 Podfile\\n[Van] feat：清理无用代码\\n[Van] feat:QVAIVideoEngineAI 升级6.2.9\\n[Van] feat:2.13.0分支创建\\n[zhangqifan] fix: %@\\n[zhangqifan] feat: 更新字符串\\n[Van] feat：归因todocode 增加来源"}