{"product_name":"VivaCut","build_number":"1403","build_type":"build_adhoc","version":"2.8.0","time":"2021-12-06_14_38","branch":"dev_2.8.0_feat_oss","download_path":"http://10.0.32.129:8888/VivaCut/VivaCut_2.8.0_dev_2.8.0_feat_oss_build_adhoc_1403_2021-12-06_14_38.ipa","jenkins_path":"http://10.0.32.129:8080/job/iOS%20AutoBuild%VivaCut/1403/","changelog":"* [张启帆] fix: missing pod\\n* [张启帆] fix: Podfile\\n* [Van] feat:创建280分支\\n* [张启帆] fix: appconfig 无法更新配置\\n* [Van] feat:2.7.6 版本建立\\n* [Van] feat:更新字符串\\n* [zhangmiao] feat: 修改为指定2.7.5分支\\n* [zhangmiao] feat: 分支修改\\n* [fmxfmx] feat:更新引擎版本修复字幕行间距相关问题\\n* [Van] feat:修改routercenter 到2.0.3"}