{"product_name":"VivaCut","build_number":"4825","build_type":"build_adhoc","version":"3.8.2","time":"2024-09-05_18_01","branch":"dev_3.8.8","download_path":"http://10.0.32.62:8888/VivaCut/VivaCut_3.8.2_dev_3.8.8_build_adhoc_4825_2024-09-05_18_01.ipa","jenkins_path":"http://10.0.32.62:8080/job/iOS%20AutoBuild%VivaCut/4825/","changelog":"[chaojie.zheng] feat(scope): album 388\\n[chaojie.zheng] feat(scope): creater 388\\n[chaojie.zheng] feat(scope): 3.8.8 pod 分支修改\\n[chaojie.zheng] feat(scope): 订阅分支修改 388\\n[chaojie.zheng] feat(scope): 3.8.8 string\\n[chaojie.zheng] feat(scope): string\\n[FengmingXiao] feat:新增AppKey\\n[FengmingXiao] feat:修改版本库\\n[FengmingXiao] feat:修改引擎版本\\n[chaojie.zheng] feat(scope): 新增String"}