{"product_name":"VivaCut","build_number":"2071","build_type":"build_adhoc","version":"2.12.7","time":"2022-05-11_10_27","branch":"dev_2.12.7_feat_V6","download_path":"http://10.0.32.32:8888/VivaCut/VivaCut_2.12.7_dev_2.12.7_feat_V6_build_adhoc_2071_2022-05-11_10_27.ipa","jenkins_path":"http://10.0.32.32:8080/job/iOS%20AutoBuild%VivaCut/2071/","changelog":"[Van] feat:更新V6引擎\\n[zhangqifan] fix: %@\\n[zhangqifan] feat: 更新字符串\\n[Van] feat：归因todocode 增加来源\\n[zhangqifan] fix: add loginkit\\n[Van] feat:更新引擎vivacut_29108_20220506_1651806751\\n[yvan] feat:翻译\\n[zhaoyunyi] feat: 1. 新增性能监控页面 2. 修改日志没有参数的情况上报\\n[zhaoyunyi] fix: 修改podfile\\n[zhangqifan] feat: 更新字符串"}