{"product_name":"VivaCut","build_number":"3688","build_type":"build_adhoc","version":"3.1.4","time":"2023-02-20_14_51","branch":"dev_3.0.9_recommend","download_path":"http://10.0.32.62:8888/VivaCut/VivaCut_3.1.4_dev_3.0.9_recommend_build_adhoc_3688_2023-02-20_14_51.ipa","jenkins_path":"http://10.0.32.62:8080/job/iOS%20AutoBuild%VivaCut/3688/","changelog":"[sheepzhangzhang] feat: 升级AppKey版本号\\n[sheepzhangzhang] feat: 升级版本号\\n[sheepzhangzhang] feat: todocode归因记录\\n[sheepzhangzhang] feat: 推荐个性化配置\\n[sheepzhangzhang] feat: 存储归因信息campain和adset\\n[sheepzhangzhang] feat: 修改分支\\n[sheepzhangzhang] feat: 修改分支\\n[sheepzhangzhang] feat: 个性化配置接口\\n[zhaoyunyi] fix: strings updated\\n[zhaoyunyi] fix: strings update"}